{
  "request_id": "demo-thai-classification-auto-001",
  "task_type": "classification",
  "task_description": "Classify Thai legal document text into the correct document category. Return only one label from the labels present in the seed dataset.",
  "synthetic_target_count": 1800,
  "seed_data": {
    "type": "file",
    "path": "data/raw/thai-text-classification-seed-data.json",
    "format": "json",
    "text_field": "text",
    "label_field": "label"
  },
  "outputs": {
    "run_root": "runs"
  }
}
